django_shell/__init__.py
django_shell/djshell.py
django_shell-1.0.2.dist-info/DESCRIPTION.rst
django_shell-1.0.2.dist-info/METADATA
django_shell-1.0.2.dist-info/RECORD
django_shell-1.0.2.dist-info/WHEEL
django_shell-1.0.2.dist-info/metadata.json
django_shell-1.0.2.dist-info/top_level.txt
